Metadata-Version: 2.1
Name: sdatest-printer
Version: 1.0.0
Summary: a boilerplate to publish packages
Home-page: UNKNOWN
Author: Eimantas Blaževičius
Author-email: eima.blazevicius@gmail.com
License: MIT
Platform: UNKNOWN
Classifier: License :: OSI Approved :: MIT License
Classifier: Programming Language :: Python :: 3
Classifier: Programming Language :: Python :: 3.7
